boogiepi/__init__.py
boogiepi-0.3.6.8.1.dist-info/LICENSE
boogiepi-0.3.6.8.1.dist-info/METADATA
boogiepi-0.3.6.8.1.dist-info/WHEEL
boogiepi-0.3.6.8.1.dist-info/top_level.txt
boogiepi-0.3.6.8.1.dist-info/RECORD
