Metadata-Version: 2.1
Name: boogiepi
Version: 0.3.6.8.1
Summary: Library for sensor data processing and visualization
Home-page: https://github.com/BoogieMobile/boogiepi
Author: Chris Laprade
Author-email: chris@boogiemobile.net
License: MIT
Platform: UNKNOWN
Classifier: License :: OSI Approved :: MIT License
Classifier: Intended Audience :: Developers
Classifier: Development Status :: 1 - Planning
Classifier: Programming Language :: Python :: 3.6
Classifier: Programming Language :: Python :: 3.7
Classifier: Operating System :: OS Independent
Requires-Python: >=3.6
